karby/__init__.py
karby/parameter_manager.py
karby/sca_tool_scan.py
karby/sca_apis/Dependabot.py
karby/sca_apis/OSSIndex.py
karby/sca_apis/OWASP.py
karby/sca_apis/SCAFactory.py
karby/sca_apis/SCAScanTool.py
karby/sca_apis/Scantist.py
karby/sca_apis/Snyk-Deprecated.py
karby/sca_apis/Snyk.py
karby/sca_apis/Steady.py
karby/sca_apis/Whitesource.py
karby/sca_apis/__init__.py
karby/util/__init__.py
karby/util/constants.py
karby/util/helpers.py
karby/util/pomUtils.py
karby/util/settings.py
karby/util/snyk_crawler.py
karby/util/test.py
karby/util/models/ComponentReport.py
karby/util/models/IssueReport.py
karby/util/models/__init__.py
scantist_karby-4.2.0.dist-info/LICENSE
scantist_karby-4.2.0.dist-info/METADATA
scantist_karby-4.2.0.dist-info/WHEEL
scantist_karby-4.2.0.dist-info/entry_points.txt
scantist_karby-4.2.0.dist-info/top_level.txt
scantist_karby-4.2.0.dist-info/RECORD
