Metadata-Version: 2.1
Name: scantist-karby
Version: 4.2.0
Summary: scan the provided projects by using whitesource or scantist, and convert the result into scantist's format
Author: scantist
Author-email: lida@scantist.com
License: UNKNOWN
Platform: UNKNOWN
Classifier: Programming Language :: Python :: 3
Classifier: License :: OSI Approved :: MIT License
Classifier: Operating System :: OS Independent
License-File: LICENSE
Requires-Dist: requests
Requires-Dist: lxml
